Mvulib/Mvulib.ctf
Mvulib/__init__.py
Mvulib_R2024a-24.1.dist-info/METADATA
Mvulib_R2024a-24.1.dist-info/WHEEL
Mvulib_R2024a-24.1.dist-info/top_level.txt
Mvulib_R2024a-24.1.dist-info/RECORD
