Metadata-Version: 2.1
Name: Mvulib-R2024a
Version: 24.1
Summary: A Python interface to Mvulib
Home-page: https://www.mathworks.com/
Author: MathWorks
Platform: Linux
Platform: Windows
Platform: macOS
